<?xml version="1.0" encoding="UTF-8" ?>
<!DOCTYPE mapper
 PUBLIC "-//mybatis.org//DTD Mapper 3.0//EN"
 "https://mybatis.org/dtd/mybatis-3-mapper.dtd">
<mapper namespace="Chart">
	
	<select id="get10SC" resultType="bubbleChartVO">
		
		<![CDATA[select cmc , cnt from comments where age_range = 10 and rownum <= 10 order by cnt desc]]>

	</select>
	
	<select id="get20SC" resultType="bubbleChartVO">
		
		<![CDATA[select cmc , cnt from comments where age_range = 20 and rownum <= 10 order by cnt desc]]>

	</select>
	
	<select id="get30SC" resultType="bubbleChartVO">
		
		<![CDATA[select cmc , cnt from comments where age_range = 30 and rownum <= 10 order by cnt desc]]>

	</select>
	
	<select id="get40SC" resultType="bubbleChartVO">
		
		<![CDATA[select cmc , cnt from comments where age_range = 40 and rownum <= 10 order by cnt desc]]>

	</select>
	
	
	<select id="get50SC" resultType="bubbleChartVO">
		
		<![CDATA[select cmc , cnt from comments where age_range = 50 and rownum <= 10 order by cnt desc]]>

	</select>
	
</mapper>